MANIFEST.in
README.md
pyproject.toml
setup.py
streamlit_mermaid/__init__.py
streamlit_mermaid.egg-info/PKG-INFO
streamlit_mermaid.egg-info/SOURCES.txt
streamlit_mermaid.egg-info/dependency_links.txt
streamlit_mermaid.egg-info/requires.txt
streamlit_mermaid.egg-info/top_level.txt
streamlit_mermaid/frontend/build/asset-manifest.json
streamlit_mermaid/frontend/build/index.html
streamlit_mermaid/frontend/build/static/js/120.020e33a2.chunk.js
streamlit_mermaid/frontend/build/static/js/120.020e33a2.chunk.js.LICENSE.txt
streamlit_mermaid/frontend/build/static/js/120.020e33a2.chunk.js.map
streamlit_mermaid/frontend/build/static/js/181.8f9a6c49.chunk.js
streamlit_mermaid/frontend/build/static/js/181.8f9a6c49.chunk.js.map
streamlit_mermaid/frontend/build/static/js/190.98487c50.chunk.js
streamlit_mermaid/frontend/build/static/js/190.98487c50.chunk.js.map
streamlit_mermaid/frontend/build/static/js/247.19fa80f4.chunk.js
streamlit_mermaid/frontend/build/static/js/247.19fa80f4.chunk.js.map
streamlit_mermaid/frontend/build/static/js/256.228a0048.chunk.js
streamlit_mermaid/frontend/build/static/js/256.228a0048.chunk.js.map
streamlit_mermaid/frontend/build/static/js/278.eeb3ee5a.chunk.js
streamlit_mermaid/frontend/build/static/js/278.eeb3ee5a.chunk.js.map
streamlit_mermaid/frontend/build/static/js/301.974db03e.chunk.js
streamlit_mermaid/frontend/build/static/js/301.974db03e.chunk.js.map
streamlit_mermaid/frontend/build/static/js/331.dbc131ab.chunk.js
streamlit_mermaid/frontend/build/static/js/331.dbc131ab.chunk.js.map
streamlit_mermaid/frontend/build/static/js/53.9eb5e9fa.chunk.js
streamlit_mermaid/frontend/build/static/js/53.9eb5e9fa.chunk.js.map
streamlit_mermaid/frontend/build/static/js/559.4d79c8d2.chunk.js
streamlit_mermaid/frontend/build/static/js/559.4d79c8d2.chunk.js.map
streamlit_mermaid/frontend/build/static/js/562.97f72871.chunk.js
streamlit_mermaid/frontend/build/static/js/562.97f72871.chunk.js.map
streamlit_mermaid/frontend/build/static/js/573.ec7c4efc.chunk.js
streamlit_mermaid/frontend/build/static/js/573.ec7c4efc.chunk.js.map
streamlit_mermaid/frontend/build/static/js/613.70b66805.chunk.js
streamlit_mermaid/frontend/build/static/js/613.70b66805.chunk.js.map
